fw_patches/ApplyPatch.py
fw_patches/FwConst.py
fw_patches/Generate.py
fw_patches/Prepare.py
fw_patches/__init__.py
fw_patches/tools.py
fw_patches2/ApplyPatch.py
fw_patches2/Const.py
fw_patches2/Generate.py
fw_patches2/Prepare.py
fw_patches2/__init__.py
fw_patches2/module_apply.py
fw_patches2/module_generate.py
fw_patches2/module_patchdir.py
fw_patches2/module_prepare.py
fw_patches2/tools.py
fwpt_apatcher/ApatcherClass.py
fwpt_apatcher/ApatcherGDocs.py
fwpt_apatcher/ApatcherGUI.py
fwpt_apatcher/ApatcherGendocs.py
fwpt_apatcher/ApatcherMenu.py
fwpt_apatcher/ApatcherUnittest.py
fwpt_apatcher/ApatcherUtils.py
fwpt_apatcher/__init__.py
fwpt_apatcher/apather_do.py
fwpt_apatcher/icon.jpg
fwpt_apatcher/mainwindow.ui
fwpt_apatcher-1.0.4.dist-info/DESCRIPTION.rst
fwpt_apatcher-1.0.4.dist-info/METADATA
fwpt_apatcher-1.0.4.dist-info/RECORD
fwpt_apatcher-1.0.4.dist-info/WHEEL
fwpt_apatcher-1.0.4.dist-info/metadata.json
fwpt_apatcher-1.0.4.dist-info/top_level.txt
