Metadata-Version: 2.0
Name: fwpt-apatcher
Version: 1.0.4
Summary: Программа формирования template и сопроводительной документации для патчей 
Home-page: UNKNOWN
Author: alex1ops
Author-email: ale51098223@yandex.ru
License: MIT
Platform: UNKNOWN
Requires-Dist: docxtpl
Requires-Dist: httplib2
Requires-Dist: lxml (>3.0.0)
Requires-Dist: pymorphy2
Requires-Dist: pyqt5 (==5.8.2)
Requires-Dist: python-docx
Requires-Dist: sip (==4.19.2)
